fdserial/__init__.py
fdserial/__main__.py
fdserial/api.py
fdserial/utils.py
freedeck_serial_api-0.2.0.dist-info/METADATA
freedeck_serial_api-0.2.0.dist-info/WHEEL
freedeck_serial_api-0.2.0.dist-info/entry_points.txt
freedeck_serial_api-0.2.0.dist-info/top_level.txt
freedeck_serial_api-0.2.0.dist-info/RECORD
