Metadata-Version: 2.1
Name: freedeck-serial-api
Version: 0.2.0
Summary: A python lib to speak to the FreeDeck over serial
Home-page: https://github.com/freeyourstream/freedeck-serial-api-python
Author: Kilian Gosewisch
Author-email: kilian2798@gmail.com
License: MIT
Platform: UNKNOWN
Classifier: License :: OSI Approved :: MIT License
Classifier: Programming Language :: Python :: 3
Classifier: Programming Language :: Python :: 3.7
Requires-Dist: pyserial (==3.5)
